{"version": 0.6, "generator": "Overpass API 0.7.62.10 2d4cfc48", "osm3s": {"timestamp_osm_base": "2026-02-11T15:10:45Z", "copyright": "The data included in this document is from www.openstreetmap.org. The data is made available under ODbL."}, "elements": [{"type": "way", "id": 43189978, "center": {"lat": 60.830873, "lon": 14.8752115}, "tags": {"leisure": "nature_reserve", "lst:ajour": "2004-06-23", "lst:area_ha": "20.701309", "lst:ref": "2002173", "lst:typ": "K", "name": "Vaver\u00f6n", "snowmobile": "no", "start_date": "2004-04-06", "wikidata": "Q30161766"}}, {"type": "way", "id": 102865242, "center": {"lat": 57.8251721, "lon": 15.4187793}, "tags": {"leisure": "nature_reserve", "lst:area_ha": "20.316890932", "lst:ref": "2001720", "lst:url": "http://www.lansstyrelsen.se/ostergotland/amnen/naturvard/skyddadnatur/naturreservat/", "name": "Tattaremossens DR", "source": "L\u00e4nsstyrelsen i \u00d6sterg\u00f6tlands l\u00e4n (gis.lst.se)", "wikidata": "Q30161733"}}, {"type": "way", "id": 394431659, "center": {"lat": 65.4688225, "lon": 19.5961378}, "tags": {"leisure": "nature_reserve", "lst:area_ha": "108.1", "lst:beslutsdatum": "2015-03-09", "lst:diarienr": "511-10094-2012", "lst:ref": "2040489", "lst:tillkomst": "2015-04-03", "name": "Stor-Abborrtj\u00e4rnen", "wikidata": "Q30161724"}}, {"type": "way", "id": 1230706362, "center": {"lat": 56.0886655, "lon": 14.3826714}, "tags": {"NVRID": "2044290", "boundary": "protected_area", "leisure": "nature_reserve", "name": "Fl\u00f6t\u00f6 naturreservat", "operator": "L\u00e4nsstyrelsen i Sk\u00e5ne l\u00e4n", "protect_class": "4", "protection_title": "Naturreservat", "ref:DIARIENR": "511-8548-2015", "source": "Naturv\u00e5rdsverket", "start_date": "2015-10-10", "website": "https://www.lansstyrelsen.se/skane/besoksmal/naturreservat/kristianstad/floto.html", "wikidata": "Q30161777"}}]}